adafruit_lis2mdl.py
adafruit_circuitpython_lis2mdl-2.1.28.dist-info/licenses/LICENSE
adafruit_circuitpython_lis2mdl-2.1.28.dist-info/METADATA
adafruit_circuitpython_lis2mdl-2.1.28.dist-info/WHEEL
adafruit_circuitpython_lis2mdl-2.1.28.dist-info/top_level.txt
adafruit_circuitpython_lis2mdl-2.1.28.dist-info/RECORD
