Metadata-Version: 2.4
Name: adafruit-circuitpython-lis2mdl
Version: 2.1.28
Summary: CircuitPython library for LIS2MDL 3-axis magnetometer.
Author-email: Adafruit Industries <circuitpython@adafruit.com>
License: MIT
Project-URL: Homepage, https://github.com/adafruit/Adafruit_CircuitPython_LIS2MDL
Keywords: adafruit,lsm303,lis2mdl,3-dof,3-axis,6dof,6-dof,magnetometer,axisbreakout,hardware,micropython,circuitpython
Classifier: Intended Audience :: Developers
Classifier: Topic :: Software Development :: Libraries
Classifier: Topic :: Software Development :: Embedded Systems
Classifier: Topic :: System :: Hardware
Classifier: License :: OSI Approved :: MIT License
Classifier: Programming Language :: Python :: 3
License-File: LICENSE
Requires-Dist: Adafruit-Blinka
Requires-Dist: adafruit-circuitpython-register
Requires-Dist: adafruit-circuitpython-busdevice
Requires-Dist: typing-extensions~=4.0
Provides-Extra: optional
Dynamic: license-file
